{
	"info": {
		"_postman_id": "d3367eda-b9e9-4e6f-b2ee-50234a740aba",
		"name": "intexsoft-backend",
		"schema": "https://schema.getpostman.com/json/collection/v2.1.0/collection.json",
		"_exporter_id": "20036212"
	},
	"item": [
		{
			"name": "auth",
			"item": [
				{
					"name": "Register",
					"request": {
						"method": "POST",
						"header": [],
						"body": {
							"mode": "raw",
							"raw": "{\r\n    \"email\": \"kirill.vasko@gmail.com\",\r\n    \"password\": \"pA55w0rd1\",\r\n    \"firstName\": \"Kirill\",\r\n    \"lastName\": \"Vasko\"\r\n}",
							"options": {
								"raw": {
									"language": "json"
								}
							}
						},
						"url": {
							"raw": "{{api}}/auth/register",
							"host": [
								"{{api}}"
							],
							"path": [
								"auth",
								"register"
							]
						}
					},
					"response": []
				},
				{
					"name": "Login",
					"request": {
						"method": "POST",
						"header": [],
						"body": {
							"mode": "raw",
							"raw": "{\r\n    \"email\": \"kirill.vasko@gmail.com\",\r\n    \"password\": \"pA55w0rd1\"\r\n}",
							"options": {
								"raw": {
									"language": "json"
								}
							}
						},
						"url": {
							"raw": "{{api}}/auth/login",
							"host": [
								"{{api}}"
							],
							"path": [
								"auth",
								"login"
							]
						}
					},
					"response": []
				},
				{
					"name": "Refresh",
					"protocolProfileBehavior": {
						"disableBodyPruning": true
					},
					"request": {
						"method": "GET",
						"header": [],
						"body": {
							"mode": "raw",
							"raw": "{\r\n    \"refreshToken\": \"eyJhbGciOiJIUzI1NiIsInR5cCI6IkpXVCJ9.eyJpZCI6MSwiaWF0IjoxNjY4MjczOTE2LCJleHAiOjE2Njg1MzMxMTZ9.QDAjbJERMjjn9uKTrsUDUUsmTSwBPLYNrd7CRMHnTRk\"\r\n}",
							"options": {
								"raw": {
									"language": "json"
								}
							}
						},
						"url": {
							"raw": "{{api}}/auth/refresh",
							"host": [
								"{{api}}"
							],
							"path": [
								"auth",
								"refresh"
							]
						}
					},
					"response": []
				}
			]
		},
		{
			"name": "user",
			"item": [
				{
					"name": "CurrentUser",
					"request": {
						"method": "GET",
						"header": [
							{
								"key": "Authorization",
								"value": "Bearer {{token}}",
								"type": "text"
							}
						],
						"url": {
							"raw": "{{api}}/user/",
							"host": [
								"{{api}}"
							],
							"path": [
								"user",
								""
							]
						}
					},
					"response": []
				},
				{
					"name": "UpdateCurrentUser",
					"request": {
						"method": "PATCH",
						"header": [
							{
								"key": "Authorization",
								"value": "Bearer {{token}}",
								"type": "text"
							}
						],
						"body": {
							"mode": "raw",
							"raw": "{\r\n    \"firstName\": \"Kirill\"\r\n}",
							"options": {
								"raw": {
									"language": "json"
								}
							}
						},
						"url": {
							"raw": "{{api}}/user/",
							"host": [
								"{{api}}"
							],
							"path": [
								"user",
								""
							]
						}
					},
					"response": []
				},
				{
					"name": "DeleteCurrentUser",
					"request": {
						"method": "DELETE",
						"header": [
							{
								"key": "Authorization",
								"value": "Bearer {{token}}",
								"type": "text"
							}
						],
						"url": {
							"raw": "{{api}}/user/",
							"host": [
								"{{api}}"
							],
							"path": [
								"user",
								""
							]
						}
					},
					"response": []
				},
				{
					"name": "UserById",
					"request": {
						"method": "GET",
						"header": [
							{
								"key": "Authorization",
								"value": "Bearer {{token}}",
								"type": "text"
							}
						],
						"url": {
							"raw": "{{api}}/user/7",
							"host": [
								"{{api}}"
							],
							"path": [
								"user",
								"7"
							]
						}
					},
					"response": []
				}
			]
		}
	],
	"event": [
		{
			"listen": "prerequest",
			"script": {
				"type": "text/javascript",
				"exec": [
					""
				]
			}
		},
		{
			"listen": "test",
			"script": {
				"type": "text/javascript",
				"exec": [
					""
				]
			}
		}
	],
	"variable": [
		{
			"key": "api",
			"value": "http://localhost:3000/api",
			"type": "string"
		},
		{
			"key": "token",
			"value": "eyJhbGciOiJIUzI1NiIsInR5cCI6IkpXVCJ9.eyJpZCI6MSwiaWF0IjoxNjY5MDM1OTc0LCJleHAiOjE2NjkwMzY4NzR9.qz_1O7v_nUy3_0lOY_Atn-bowBx1bF_Ny1_dnlOgOWU",
			"type": "string"
		}
	]
}